kvbiii_plots/__init__.py
kvbiii_plots/eda/eda_plots.py
kvbiii_plots-0.2.0.dist-info/METADATA
kvbiii_plots-0.2.0.dist-info/WHEEL
kvbiii_plots-0.2.0.dist-info/top_level.txt
kvbiii_plots-0.2.0.dist-info/RECORD
