Metadata-Version: 2.4
Name: kvbiii_plots
Version: 0.2.0
Summary: A collection of plotting functions for data visualization in Python.
Author-email: Jakub Kościan <kuba.koscian001@gmail.com>
Maintainer-email: Jakub Kościan <kuba.koscian001@gmail.com>
Project-URL: homepage, https://github.com/kvbiii/kvbiii-plots
Project-URL: repository, https://github.com/kvbiii/kvbiii-plots
Keywords: data visualization,plotting,matplotlib,seaborn
Classifier: Intended Audience :: Developers
Classifier: License :: OSI Approved :: MIT License
Classifier: Programming Language :: Python :: 3.10
Classifier: Programming Language :: Python :: 3.11
Classifier: Programming Language :: Python :: 3.12
Requires-Python: >=3.10
Requires-Dist: pandas==2.3.1
Requires-Dist: plotly[kaleido]==6.2.0
Requires-Dist: setuptools==65.5.0
